TestUnusialMath/Math.py
TestUnusialMath/__init__.py
TestUnusialMath-0.0.1.dist-info/LICENSE.txt
TestUnusialMath-0.0.1.dist-info/METADATA
TestUnusialMath-0.0.1.dist-info/WHEEL
TestUnusialMath-0.0.1.dist-info/top_level.txt
TestUnusialMath-0.0.1.dist-info/RECORD
