Metadata-Version: 2.1
Name: TestUnusialMath
Version: 0.0.1
Summary: Test library
Home-page: https://github.com/iderevitskiy/TestUnusialMath.git
Author: Ivan Derevitskii
Author-email: iderevitskiy@gmail.com
License: UNKNOWN
Platform: UNKNOWN
Classifier: Programming Language :: Python :: 3
Classifier: License :: OSI Approved :: MIT License
Classifier: Operating System :: OS Independent
Requires-Python: >=3.6
License-File: LICENSE.txt
